pyboat/LICENSE
pyboat/__init__.py
pyboat/__main__.py
pyboat/api.py
pyboat/core.py
pyboat/ensemble_measures.py
pyboat/logo_circ128x128.png
pyboat/plotting.py
pyboat/ssg.py
pyboat/ui/analysis_parameters.py
pyboat/ui/analyzer.py
pyboat/ui/batch_process.py
pyboat/ui/data_viewer.py
pyboat/ui/defaults.py
pyboat/ui/start_menu.py
pyboat/ui/style.py
pyboat/ui/synth_gen.py
pyboat/ui/util.py
pyboat-1.0.0.dist-info/entry_points.txt
pyboat-1.0.0.dist-info/licenses/LICENSE
pyboat-1.0.0.dist-info/WHEEL
pyboat-1.0.0.dist-info/METADATA
pyboat-1.0.0.dist-info/RECORD
