Metadata-Version: 2.4
Name: pyboat
Version: 1.0.0
Summary: Time-frequency analysis of noisy non-stationary signals with Morlet Wavelets.
Author-email: Gregor Mönke <tensionheadx@gmail.com>
Requires-Python: >=3.11
License-Expression: GPL-3.0-or-later
Classifier: Intended Audience :: Science/Research
License-File: LICENSE
Requires-Dist: numpy >=2
Requires-Dist: scipy >=1.15
Requires-Dist: matplotlib >=3.10
Requires-Dist: pandas >=2
Requires-Dist: PyQt6 >=6.8
Requires-Dist: openpyxl >=3.1.3
Project-URL: Projectpage, https://github.com/tensionhead/pyBOAT
